cmd_mox/__init__.py
cmd_mox/_validators.py
cmd_mox/command_runner.py
cmd_mox/comparators.py
cmd_mox/controller.py
cmd_mox/environment.py
cmd_mox/errors.py
cmd_mox/expectations.py
cmd_mox/passthrough.py
cmd_mox/platform.py
cmd_mox/pytest_plugin.py
cmd_mox/shim.py
cmd_mox/shimgen.py
cmd_mox/test_doubles.py
cmd_mox/verifiers.py
cmd_mox/ipc/__init__.py
cmd_mox/ipc/client.py
cmd_mox/ipc/constants.py
cmd_mox/ipc/json_utils.py
cmd_mox/ipc/models.py
cmd_mox/ipc/server.py
cmd_mox/ipc/socket_utils.py
cmd_mox/unittests/conftest.py
cmd_mox/unittests/pytest_plugin_module_utils.py
cmd_mox/unittests/test_command_runner.py
cmd_mox/unittests/test_controller_basic.py
cmd_mox/unittests/test_controller_env.py
cmd_mox/unittests/test_controller_environment_manager.py
cmd_mox/unittests/test_controller_handler.py
cmd_mox/unittests/test_controller_lifecycle.py
cmd_mox/unittests/test_controller_passthrough.py
cmd_mox/unittests/test_controller_shim.py
cmd_mox/unittests/test_environment.py
cmd_mox/unittests/test_expectations.py
cmd_mox/unittests/test_invocation_journal.py
cmd_mox/unittests/test_ipc_server.py
cmd_mox/unittests/test_order_verifier.py
cmd_mox/unittests/test_passthrough.py
cmd_mox/unittests/test_pytest_plugin.py
cmd_mox/unittests/test_pytest_plugin_module_utils_unit.py
cmd_mox/unittests/test_shim.py
cmd_mox/unittests/test_shim_generation.py
cmd_mox/unittests/test_spy_assertions.py
cmd_mox/unittests/test_validators.py
cmd_mox/unittests/test_verification_errors.py
cmd_mox/unittests/test_verifier_helpers.py
cmd_mox-0.1.0.dist-info/licenses/LICENSE
tests/test_comparators.py
tests/test_controller_bdd.py
tests/test_controller_helpers.py
tests/test_ipc_behaviour.py
tests/test_ipc_client_unit.py
tests/test_ipc_json_utils.py
tests/test_ipc_models_unit.py
tests/test_ipc_public_api.py
tests/test_ipc_server_callbacks.py
tests/test_ipc_socket_utils.py
tests/test_order_verifier_bdd.py
tests/test_platform_support.py
tests/test_pytest_plugin_bdd.py
tests/test_pytest_plugin_formatting.py
tests/test_pytest_plugin_manager.py
cmd_mox-0.1.0.dist-info/METADATA
cmd_mox-0.1.0.dist-info/WHEEL
cmd_mox-0.1.0.dist-info/top_level.txt
cmd_mox-0.1.0.dist-info/RECORD
