Metadata-Version: 2.4
Name: cmd-mox
Version: 0.1.0
Summary: cmd-mox package
Author-email: Payton McIntosh <pmcintosh@df12.net>
License: ISC
Requires-Python: >=3.11
License-File: LICENSE
Dynamic: license-file
